ibex/__init__.py
ibex/dataloader.py
ibex/inference.py
ibex/model.py
ibex/predict.py
ibex/py.typed
ibex/refine.py
ibex/utils.py
ibex/loss/__init__.py
ibex/loss/aligned_rmsd.py
ibex/loss/loss.py
ibex/openfold/__init__.py
ibex/openfold/model.py
ibex/openfold/resources/__init__.py
ibex/openfold/resources/stereo_chemical_props.txt
ibex/openfold/utils/__init__.py
ibex/openfold/utils/data_transforms.py
ibex/openfold/utils/feats.py
ibex/openfold/utils/loss.py
ibex/openfold/utils/precision_utils.py
ibex/openfold/utils/protein.py
ibex/openfold/utils/residue_constants.py
ibex/openfold/utils/rigid_utils.py
ibex/openfold/utils/tensor_utils.py
prescient_ibex-0.2.3.dist-info/licenses/LICENSE
prescient_ibex-0.2.3.dist-info/METADATA
prescient_ibex-0.2.3.dist-info/WHEEL
prescient_ibex-0.2.3.dist-info/entry_points.txt
prescient_ibex-0.2.3.dist-info/top_level.txt
prescient_ibex-0.2.3.dist-info/RECORD
