Metadata-Version: 2.4
Name: prescient-ibex
Version: 0.2.3
Summary: Lightweight antibody structure prediction tool (arXiv:2507.09054)
Author: Prescient Design
Requires-Python: >=3.10
License-File: LICENSE
Requires-Dist: click<8.2.0
Requires-Dist: dm-tree
Requires-Dist: einops
Requires-Dist: esm==3.1.6
Requires-Dist: hydra-core
Requires-Dist: levenshtein
Requires-Dist: lightning>=2.5.0.post0
Requires-Dist: loguru>=0.7.3
Requires-Dist: ml-collections>=1.0.0
Requires-Dist: numpy>=1.26.4
Requires-Dist: omegaconf>=2.3.0
Requires-Dist: openmm>=8.2.0
Requires-Dist: pandas>=2.2.3
Requires-Dist: pdbfixer
Requires-Dist: pyparsing>=3.2.3
Requires-Dist: python-box>=7.3.2
Requires-Dist: s3fs>=2025.2.0
Requires-Dist: scipy>=1.10.1
Requires-Dist: sentencepiece
Requires-Dist: torch>=2.5.1
Requires-Dist: tqdm
Requires-Dist: transformers
Requires-Dist: typer>=0.15.2
Requires-Dist: wandb>=0.19.8
Provides-Extra: analysis
Requires-Dist: matplotlib>=3.10.1; extra == "analysis"
Requires-Dist: py3dmol>=2.4.2; extra == "analysis"
Requires-Dist: seaborn>=0.13.2; extra == "analysis"
Dynamic: license-file
